{
  "schemaName": "stock_ticks_latest",
  "dimensionFieldSpecs": [
    { "name": "S", "dataType": "STRING" },
    { "name": "T", "dataType": "STRING" }
  ],
  "metricFieldSpecs": [
    { "name": "o", "dataType": "DOUBLE" },
    { "name": "h", "dataType": "DOUBLE" },
    { "name": "l", "dataType": "DOUBLE" },
    { "name": "c", "dataType": "DOUBLE" },
    { "name": "v", "dataType": "LONG" },
    { "name": "n", "dataType": "LONG" },
    { "name": "vw", "dataType": "DOUBLE" }
  ],
  "dateTimeFieldSpecs": [
    {
      "name": "timestamp",
      "dataType": "TIMESTAMP",
      "format": "1:MILLISECONDS:EPOCH",
      "granularity": "1:MILLISECONDS"
    }
  ]
}
